README.md
setup.py
mcp_rdkit/__init__.py
mcp_rdkit/__main__.py
mcp_rdkit/rdkit_helper.py
mcp_rdkit.egg-info/PKG-INFO
mcp_rdkit.egg-info/SOURCES.txt
mcp_rdkit.egg-info/dependency_links.txt
mcp_rdkit.egg-info/requires.txt
mcp_rdkit.egg-info/top_level.txt