Metadata-Version: 2.1
Name: mcp_rdkit
Version: 0.1.8
Summary: A package for RDKit integration with MCP
Author: Shashank Shekhar Shukla
Author-email: shukla20shashankshekhar@gmail.com
Project-URL: Documentation, https://github.com/s20ss/mcp_rdkit#readme
Project-URL: Source, https://github.com/s20ss/mcp_rdkit
Project-URL: Issues, https://github.com/s20ss/mcp_rdkit/issues
Keywords: RDKit,MCP,cheminformatics,molecular visualization,descriptor calculation,Claude
Classifier: Programming Language :: Python :: 3
Classifier: License :: OSI Approved :: MIT License
Classifier: Operating System :: OS Independent
Requires-Python: >=3.12
Requires-Dist: rdkit
Requires-Dist: mcp
Requires-Dist: pandas
Requires-Dist: requests
